README.rst
setup.py
pylev3/Levenshtein.py
pylev3/__init__.py
pylev3/base.py
pylev3.egg-info/PKG-INFO
pylev3.egg-info/SOURCES.txt
pylev3.egg-info/dependency_links.txt
pylev3.egg-info/top_level.txt