Metadata-Version: 1.2
Name: pylev3
Version: 1.1.0
Summary: A Python3 Levenshtein distance (re)implementation of pylev
Home-page: https://github.com/hell03end/pylev3
Author: hell03end
Author-email: hell03end@outlook.com
License: BSD License
Keywords: Levenshtein texts
Platform: All
Classifier: Intended Audience :: Developers
Classifier: Intended Audience :: Science/Research
Classifier: Intended Audience :: Education
Classifier: Development Status :: 5 - Production/Stable
Classifier: License :: OSI Approved :: BSD License
Classifier: Operating System :: OS Independent
Classifier: Programming Language :: Python
Classifier: Programming Language :: Python :: 3
Classifier: Programming Language :: Python :: 3.6
Classifier: Programming Language :: Python :: 3.5
Classifier: Programming Language :: Python :: 3.4
Classifier: Programming Language :: Python :: 3.3
Classifier: Programming Language :: Python :: Implementation :: PyPy
Classifier: Topic :: Software Development :: Libraries :: Python Modules
Requires-Python: >=3.3
